lablabel/__init__.py
lablabel/__main__.py
lablabel/lablabel.py
matildapeak_lablabel-2018.3.dist-info/METADATA
matildapeak_lablabel-2018.3.dist-info/RECORD
matildapeak_lablabel-2018.3.dist-info/WHEEL
matildapeak_lablabel-2018.3.dist-info/entry_points.txt
matildapeak_lablabel-2018.3.dist-info/top_level.txt
