Metadata-Version: 2.1
Name: matildapeak-lablabel
Version: 2018.3
Summary: A label configuration tool for GitLab
Home-page: https://gitlab.com/matilda.peak/lablabel
Author: Alan Christie
Author-email: alan.christie@matildapeak.com
License: MIT
Keywords: configuration
Platform: any
Classifier: Development Status :: 5 - Production/Stable
Classifier: Environment :: Console
Classifier: Intended Audience :: Developers
Classifier: License :: OSI Approved :: MIT License
Classifier: Programming Language :: Python :: 3.6
Classifier: Topic :: System :: Installation/Setup
Classifier: Operating System :: POSIX :: Linux
Requires-Dist: requests (==2.20.1)
